Workbook
Name BASE_OPERATION_LIST: [1]TECHSHEET!$K$29:$K$37
Name CCP_GTP_TYPES: [1]TECHSHEET!$K$52:$K$53
Name CEO_EMAIL: [1]Титульный!$F$65
Name CEO_NAME: [1]Титульный!$F$62
Name CEO_PHONE: [1]Титульный!$F$64
Name CEO_POSITION: [1]Титульный!$F$63
Name CURRENT_PERIOD: [1]Титульный!$F$12
Name CURRENT_PERIOD: #REF!
Name EXT_ORG_LA_ADDRESS: [1]Титульный!$M$102
Name EXT_ORG_LA_ADDRESS: #REF!
Name EXT_ORG_LA_INDEX: [1]Титульный!$M$103
Name EXT_ORG_LA_INDEX: #REF!
Name EXT_ORG_LA_MO: [1]Титульный!$M$100
Name EXT_ORG_LA_MO: #REF!
Name EXT_ORG_LA_MR: [1]Титульный!$M$99
Name EXT_ORG_LA_MR: #REF!
Name EXT_ORG_LA_OKTMO: [1]Титульный!$M$101
Name EXT_ORG_LA_OKTMO: #REF!
Name EXT_ORG_LA_REGION: [1]Титульный!$M$98
Name EXT_ORG_LA_REGION: #REF!
Name EXT_ORG_PA_ADDRESS: [1]Титульный!$M$108
Name EXT_ORG_PA_ADDRESS: #REF!
Name EXT_ORG_PA_INDEX: [1]Титульный!$M$109
Name EXT_ORG_PA_INDEX: #REF!
Name EXT_ORG_PA_MO: [1]Титульный!$M$106
Name EXT_ORG_PA_MO: #REF!
Name EXT_ORG_PA_MR: [1]Титульный!$M$105
Name EXT_ORG_PA_MR: #REF!
Name EXT_ORG_PA_OKTMO: [1]Титульный!$M$107
Name EXT_ORG_PA_OKTMO: #REF!
Name EXT_ORG_PA_REGION: [1]Титульный!$M$104
Name EXT_ORG_PA_REGION: #REF!
Name EXT_ORG_TAX: [1]Титульный!$M$77
Name EXT_ORG_TAX: #REF!
Name EXT_ORG_TAX_SYSTEM: [1]Титульный!$M$78
Name EXT_ORG_TAX_SYSTEM: #REF!
Name EXTENDED_TITLE_DATA: [1]Титульный!$F$45:$F$46,[1]Титульный!$F$48:$F$53,[1]Титульный!$F$55:$F$60,[1]Титульный!$F$62:$F$65
Name HEAT_DOCUMENT_URL_LIST: [1]TECHSHEET!$S$2:$S$3
Name HEAT_FUEL_CCP_GTP_BASIC_LIST: [1]TECHSHEET!$U$52:$U$55
Name HEAT_FUEL_CCP_GTP_CLAIM_LIST: [1]TECHSHEET!$S$52:$S$54
Name HEAT_FUEL_CCP_GTP_EMERGENCY_LIST: [2]TECHSHEET!$W$52:$W$54
Name HEAT_FUEL_NNZT_NEZT_MONTHLY_NNZT_AREA_1_1: '[1]Настройка расчёта ННЗТ и НЭЗТ'!$L$16
Name HEAT_FUEL_NNZT_NEZT_MONTHLY_NNZT_AREA_2: '[1]Настройка расчёта ННЗТ и НЭЗТ'!$L$22:$L$22
Name HEAT_FUEL_SPE_BASIC_LIST: [1]TECHSHEET!$U$27:$U$35
Name HEAT_FUEL_SPE_CLAIM_LIST: [1]TECHSHEET!$S$27:$S$29
Name HEAT_FUEL_SUPPLY_AVAILABLE_YEARS_LIST: [1]TECHSHEET!$S$13:$S$18
Name HEAT_NEZT_CALC_LIST: [1]TECHSHEET!$V$2:$V$4
Name HEAT_NEZT_CALC_NATURAL_GAS_LIST: [1]TECHSHEET!$U$2:$U$3
Name HEAT_TES_NNZT_VT_CALCULATION: [1]ТЭС!$BK$11
Name INN: [1]Титульный!$F$38
Name KPP: [1]Титульный!$F$39
Name LOSSES_HEADER: [1]TECHSHEET!$K$13
Name MONTH: [1]TECHSHEET!$O$2:$O$13
Name NORM_CALCULATION_TYPES: [1]TECHSHEET!$K$58:$K$60
Name OKATO: [1]Титульный!$F$41
Name ORG: [1]Титульный!$F$32
Name ORG_FULL: [1]Титульный!$F$34
Name POST_ADDRESS: [1]Титульный!$F$43
Name REGULATION_NEXT_OCTOBER_CALCULATION: [1]Титульный!$F$19
Name REGULATION_NEXT_OCTOBER_CALCULATION: #REF!

Sheet ННЗТ
B2: Расчет неснижаемого нормативного запаса топлива (ННЗТ)
B4: № п/п | C4: Наименование ТЭС | D4: Вид топлива для создания запаса | E4: Месяц | F4: ННЗТ, тнт
B6: 1 | C6: Амурская ТЭЦ-1 | D6: Уголь | E6: январь | F6: 7200
E7: февраль | F7: 7200
E8: март | F8: 7200
E9: апрель | F9: 7200
E10: май | F10: 7200
E11: июнь | F11: 7200
E12: июль | F12: 7200
E13: август | F13: 7200
E14: сентябрь | F14: 7200
E15: октябрь | F15: 7200
E16: ноябрь | F16: 7200
E17: декабрь | F17: 7200

Sheet НЭЗТ
B2: Расчет неснижаемого эксплуатационного запаса топлива (НЭЗТ)
E3: убрать, взять из Надежность | S3: блок отражаем если считаем НЭЗТ резервного топлива
B4: № п/п | C4: Наименование ТЭС | D4: Вид топлива для создания запаса | E4: Способ доставки основного топлива на ТЭС | F4: Месяц | G4: Месяц в котором поставка топлива ограничена | H4: Теплота сгорания натурального топлива по среднему значению сожженного топлива за 3 года или по данным последних замеров в случае отсутствия сжигания топлива в последние годы, ккал/кг | I4: Удельный расход условного топлива на отпуск электрической энергии при работе с установленной мощностью ТЭС на плановый год за вычетом постоянных ограничений в схеме выдачи мощности и ограничений мощности ТЭС по причине вывода оборудования в ремонт в соответствии с утвержденными графиками ремонтов энергетического и электротехнического оборудования, гут/кВт*ч | J4: Установленная электрическая мощность ТЭС (очереди оборудования ТЭС) на плановый год за вычетом постоянных ограничений в схеме выдачи мощности и ограничений мощности ТЭС по причине вывода оборудования в ремонт в соответствии с утвержденными графиками ремонтов энергетического и электротехнического оборудования, МВт | K4: Расход электрической энергии на собственные нужды тепловой электростанции за сутки, при условии функционирования с установленной плановой мощностью за вычетом постоянных ограничений в схеме выдачи мощности и ограничений мощности ТЭС по причине вывода оборудования в ремонт в соответствии с утвержденными графиками ремонтов энергетического и электротехнического оборудования, млн.кВт*ч | L4: Количество условного топлива, необходимого для функционирования ТЭС с максимальной выработкой электрической энергии в течении одних суток, т.у.т. | M4: Удельный расход условного топлива на отпуск тепловой энергии при работе по максимальному среднесуточному отпуску тепловой энергии в расчетном месяце за последние 5 лет, кг/Гкал | N4: Максимальный среднесуточный отпуск тепловой энергии за предыдущие пять лет, тыс. Гкал. | O4: Количество условного топлива, необходимого для функционирования ТЭС с максимальным отпуском тепловой энергии в расчетном месяце за предыдущие 5 лет, т.у.т. | P4: Количество условного топлива, необходимого для функционирования ТЭС в расчетном месяце в течении одних суток с максимальным суточным отпуском тепловой энергии за последние 5 лет и максимальной выработкой электрической энергии, т.у.т. | Q4: Количество суток, в течение которых обеспечивается работа ТЭС в режиме "выживания", сутки | R4: Базовая величина НЭЗТ, т.н.т. | S4: Теплота сгорания газа, ккал/мᶟ | T4: Теплота сгорания резервного топлива, ккал/кг | U4: Максимальный месячный объем ограничения газа в периоды снижения температуры за последние 8 лет, м3 | V4: НЭЗТ, т.н.т. | X4: Количество суток, при которых поставка топлива ограничена | Y4: Количество суток в расчетном месяце | Z4: Фактический среднемесячный расход топлива в расчетный месяц за предыдущие 3 года, т.н.т. | AA4: Плановый полезный отпуск тепловой энергии, в соответствии со сводным прогнозным балансом, Гкал | AB4: Плановая месячная выработка электрической энергии, в соответствии со сводным прогнозным балансом, млн кВт*ч | AC4: Расход электроэнергии на собственные нужды ТЭС, млн.кВт*ч | AD4: Удельный расход условного топлива на отпуск электрической энергии, гут/кВтч | AE4: Удельный расход условного топлива на отпуск тепловой энергии, кг/Гкал | AF4: Среднесуточный расход топлива в месяце с ограничением поставок топлива | AG4: НЭЗТ огр.пост, т.н.т.
B6: 1 | C6: Амурская ТЭЦ-1 | D6: Уголь | E6: Транспортная доставка | F6: Январь | G6: да | H6: 4712 | I6: 391.2 | J6: 281.7 | K6: 0.08 | L6: =I6*(J6*24/1000-K6) -> 2613.529 | M6: 150.6 | N6: 0.165 | O6: =M6*N6 -> 24.849 | P6: =L6+O6 -> 2638.378 | Q6: 10 | R6: =IF($H$6=0,0,P6*$Q$6*7000/$H$6) -> 39194.919 | S6: 1 | T6: =H6 -> 4712 | U6: 2 | V6: 160 | X6: 1 | Y6: 31 | Z6: 42706.56 | AA6: 160 | AB6: 0.083 | AC6: 0.024 | AD6: 249 | AE6: 165 | AF6: =(Z6+(AE6*AA6+AD6*(AB6-AC6)*(7000/H$6)))/Y6 -> 2229.9479 | AG6: 0
F7: Февраль | I7: 378.3 | J7: 281.7 | K7: 0.08 | L7: =I7*(J7*24/1000-K7) -> 2527.3466 | M7: 150.1 | N7: 0.165 | O7: =M7*N7 -> 24.7665 | P7: =L7+O7 -> 2552.1131 | R7: =IF($H$6=0,0,P7*$Q$6*7000/$H$6) -> 37913.396 | V7: 160 | Y7: 28 | Z7: 38404.3 | AA7: 160 | AB7: 0.09 | AC7: 0.02 | AD7: 248 | AE7: 169
F8: Март | I8: 397.1 | J8: 281.7 | K8: 0.08 | L8: =I8*(J8*24/1000-K8) -> 2652.9457 | M8: 151.6 | N8: 0.137 | O8: =M8*N8 -> 20.7692 | P8: =L8+O8 -> 2673.7149 | R8: =IF($H$6=0,0,P8*$Q$6*7000/$H$6) -> 39719.873 | V8: 160 | Y8: 31 | Z8: 21847.47 | AA8: 130 | AB8: 0.08 | AC8: 0.02 | AD8: 267 | AE8: 170
F9: Апрель | I9: 432 | J9: 280.3 | K9: 0.07 | L9: =I9*(J9*24/1000-K9) -> 2875.9104 | M9: 160.3 | N9: 0.76 | O9: =M9*N9 -> 121.828 | P9: =L9+O9 -> 2997.7384 | R9: =IF($H$6=0,0,P9*$Q$6*7000/$H$6) -> 44533.465 | V9: 160 | Y9: 30 | Z9: 22023.87 | AA9: 700 | AB9: 0.08 | AC9: 0.01 | AD9: 258 | AE9: 166
F10: Май | I10: 434.2 | J10: 260 | K10: 0.02 | L10: =I10*(J10*24/1000-K10) -> 2700.724 | M10: 175.2 | N10: 0.3 | O10: =M10*N10 -> 52.56 | P10: =L10+O10 -> 2753.284 | R10: =IF($H$6=0,0,P10*$Q$6*7000/$H$6) -> 40901.927 | V10: 160 | Y10: 31 | Z10: 21487.1 | AA10: 300 | AB10: 0.1 | AC10: 0.02 | AD10: 249 | AE10: 171
F11: Июнь | I11: 434.3 | J11: 260 | K11: 0.02 | L11: =I11*(J11*24/1000-K11) -> 2701.346 | M11: 176.5 | N11: 0.23 | O11: =M11*N11 -> 40.595 | P11: =L11+O11 -> 2741.941 | R11: =IF($H$6=0,0,P11*$Q$6*7000/$H$6) -> 40733.419 | V11: 160 | Y11: 30 | Z11: 13422.67 | AA11: 200 | AB11: 0.1 | AC11: 0.02 | AD11: 240 | AE11: 170
F12: Июль | I12: 454.4 | J12: 260 | K12: 0.02 | L12: =I12*(J12*24/1000-K12) -> 2826.368 | M12: 188.8 | N12: 0.21 | O12: =M12*N12 -> 39.648 | P12: =L12+O12 -> 2866.016 | R12: =IF($H$6=0,0,P12*$Q$6*7000/$H$6) -> 42576.638 | V12: 160 | Y12: 31 | Z12: 17386.67 | AA12: 200 | AB12: 0.09 | AC12: 0.03 | AD12: 248 | AE12: 168
F13: Август | I13: 457.9 | J13: 260 | K13: 0.02 | L13: =I13*(J13*24/1000-K13) -> 2848.138 | M13: 187.8 | N13: 0.2 | O13: =M13*N13 -> 37.56 | P13: =L13+O13 -> 2885.698 | R13: =IF($H$6=0,0,P13*$Q$6*7000/$H$6) -> 42869.028 | V13: 160 | Y13: 31 | Z13: 20779 | AA13: 200 | AB13: 0.06 | AC13: 0.02 | AD13: 241 | AE13: 173
F14: Сентябрь | I14: 439.8 | J14: 260 | K14: 0.02 | L14: =I14*(J14*24/1000-K14) -> 2735.556 | M14: 173.6 | N14: 0.24 | O14: =M14*N14 -> 41.664 | P14: =L14+O14 -> 2777.22 | R14: =IF($H$6=0,0,P14*$Q$6*7000/$H$6) -> 41257.513 | V14: 160 | Y14: 30 | Z14: 11523.7 | AA14: 200 | AB14: 0.07 | AC14: 0.02 | AD14: 241 | AE14: 172
F15: Октябрь | I15: 428.8 | J15: 275.7 | K15: 0.04 | L15: =I15*(J15*24/1000-K15) -> 2820.1318 | M15: 158.1 | N15: 0.68 | O15: =M15*N15 -> 107.508 | P15: =L15+O15 -> 2927.6398 | R15: =IF($H$6=0,0,P15*$Q$6*7000/$H$6) -> 43492.103 | V15: 160 | Y15: 31 | Z15: 18529 | AA15: 600 | AB15: 0.06 | AC15: 0.01 | AD15: 251 | AE15: 172
F16: Ноябрь | I16: 377.1 | J16: 281.7 | K16: 0.08 | L16: =I16*(J16*24/1000-K16) -> 2519.3297 | M16: 151.5 | N16: 0.79 | O16: =M16*N16 -> 119.685 | P16: =L16+O16 -> 2639.0147 | R16: =IF($H$6=0,0,P16*$Q$6*7000/$H$6) -> 39204.378 | V16: 160 | Y16: 30 | Z16: 36473 | AA16: 700 | AB16: 0.07 | AC16: 0.02 | AD16: 263 | AE16: 176
F17: Декабрь | I17: 393.9 | J17: 281.7 | K17: 0.1 | L17: =I17*(J17*24/1000-K17) -> 2623.6891 | M17: 150.1 | N17: 0.18 | O17: =M17*N17 -> 27.018 | P17: =L17+O17 -> 2650.7071 | R17: =IF($H$6=0,0,P17*$Q$6*7000/$H$6) -> 39378.077 | V17: 160 | Y17: 31 | Z17: 48585 | AA17: 100 | AB17: 0.08 | AC17: 0.02 | AD17: 240 | AE17: 175

Sheet НВЗТ
B2: Расчет вспомагательного запаса топлива (НВЗТ)
B4: № п/п | C4: Наименование ТЭС | D4: Вид топлива для создания запаса | E4: Месяц | F4: НВЗТ, тнт
C6: Амурская ТЭЦ-1 | D6: Уголь | E6: январь | F6: 20000
E7: февраль | F7: 30000
E8: март | F8: 20000
E9: апрель | F9: 10000
E10: май | F10: 10000
E11: июнь | F11: 10000
E12: июль | F12: 10000
E13: август | F13: 10000
E14: сентябрь | F14: 10000
E15: октябрь | F15: 20000
E16: ноябрь | F16: 20000
E17: декабрь | F17: 20000

Sheet НАЗТ
B2: Расчет аварийного запаса топлива (НАЗТ)
B4: № п/п | C4: Наименование ТЭС | D4: Вид топлива для создания запаса | E4: Месяц | F4: Максимальный суточный расход аварийного топлива для ПГУ/ГТУ, т.н.т/суток | G4: Максимальная продолжительность эксплуатации оборудования на аварийном топливе, суток | H4: НАЗТ б.в | I4: НАЗТ, т.н.т
B6: 1 | C6: Амурская ТЭЦ-1 | D6: Уголь | E6: январь | F6: 1040 | G6: 20 | H6: =$F$6*$G$6 -> 20800 | I6: 13700
E7: февраль | I7: 13800
E8: март | I8: 13736
E9: апрель | I9: 13726
E10: май | I10: 13826
E11: июнь | I11: 13947
E12: июль | I12: 13847
E13: август | I13: 13948
E14: сентябрь | I14: 13847
E15: октябрь | I15: 13736
E16: ноябрь | I16: 13958
E17: декабрь | I17: 13756

Sheet ОНЗТ
B2: Расчет общего нормативного запаса топлива (ОНЗТ)
B4: № п/п | C4: Наименование ТЭС | D4: Месяц | E4: ННЗТ, т.н.т. | F4: НЭЗТ, т.н.т. | G4: НЭЗТ огр.пост, т.н.т. | H4: НВЗТ, т.н.т. | I4: ОНЗТ, т.н.т.
B6: 1 | C6: Амурская ТЭЦ-1 | D6: январь | E6: 7200 | F6: 156.27 | G6: 0 | H6: 20000 | I6: =E6+H6+IF(G6>0,G6,F6) -> 27356.27
D7: февраль | E7: 7200 | F7: 123.9 | G7: =SUMIF(НЭЗТ!$F$6:$F$18,ОНЗТ!D7,НЭЗТ!$AG$6:$AG$18) -> 0 | H7: 30000 | I7: =E7+H7+IF(G7>0,G7,F7) -> 37323.9
D8: март | E8: 7200 | F8: 91.6 | G8: =SUMIF(НЭЗТ!$F$6:$F$18,ОНЗТ!D8,НЭЗТ!$AG$6:$AG$18) -> 0 | H8: 20000 | I8: =E8+H8+IF(G8>0,G8,F8) -> 27291.6
D9: апрель | E9: 7200 | F9: 59.2 | G9: =SUMIF(НЭЗТ!$F$6:$F$18,ОНЗТ!D9,НЭЗТ!$AG$6:$AG$18) -> 0 | H9: 10000 | I9: =E9+H9+IF(G9>0,G9,F9) -> 17259.2
D10: май | E10: 7200 | F10: 79.66 | G10: =SUMIF(НЭЗТ!$F$6:$F$18,ОНЗТ!D10,НЭЗТ!$AG$6:$AG$18) -> 0 | H10: 10000 | I10: =E10+H10+IF(G10>0,G10,F10) -> 17279.66
D11: июнь | E11: 7200 | F11: 100.12 | G11: =SUMIF(НЭЗТ!$F$6:$F$18,ОНЗТ!D11,НЭЗТ!$AG$6:$AG$18) -> 0 | H11: 10000 | I11: =E11+H11+IF(G11>0,G11,F11) -> 17300.12
D12: июль | E12: 7200 | F12: 134.96 | G12: =SUMIF(НЭЗТ!$F$6:$F$18,ОНЗТ!D12,НЭЗТ!$AG$6:$AG$18) -> 0 | H12: 10000 | I12: =E12+H12+IF(G12>0,G12,F12) -> 17334.96
D13: август | E13: 7200 | F13: 182.68 | G13: =SUMIF(НЭЗТ!$F$6:$F$18,ОНЗТ!D13,НЭЗТ!$AG$6:$AG$18) -> 0 | H13: 10000 | I13: =E13+H13+IF(G13>0,G13,F13) -> 17382.68
D14: сентябрь | E14: 7200 | F14: 230.4 | G14: =SUMIF(НЭЗТ!$F$6:$F$18,ОНЗТ!D14,НЭЗТ!$AG$6:$AG$18) -> 0 | H14: 10000 | I14: =E14+H14+IF(G14>0,G14,F14) -> 17430.4
D15: октябрь | E15: 7200 | F15: 278.12 | G15: =SUMIF(НЭЗТ!$F$6:$F$18,ОНЗТ!D15,НЭЗТ!$AG$6:$AG$18) -> 0 | H15: 20000 | I15: =E15+H15+IF(G15>0,G15,F15) -> 27478.12
D16: ноябрь | E16: 7200 | F16: 241.6 | G16: =SUMIF(НЭЗТ!$F$6:$F$18,ОНЗТ!D16,НЭЗТ!$AG$6:$AG$18) -> 0 | H16: 20000 | I16: =E16+H16+IF(G16>0,G16,F16) -> 27441.6
D17: декабрь | E17: 7200 | F17: 205.1 | G17: =SUMIF(НЭЗТ!$F$6:$F$18,ОНЗТ!D17,НЭЗТ!$AG$6:$AG$18) -> 0 | H17: 20000 | I17: =E17+H17+IF(G17>0,G17,F17) -> 27405.1

Sheet Критичность ТЭС
B2: Критичность ТЭС
E4: Влияние ТЭС на теплоснабжение потребителей | I4: Влияние нагрузки ТЭС на электроэнергетический режим энергосистемы | O4: Лист отражаем только в версии Минэнерго
M6: скрыта всегда
B7: № п/п | C7: Наименование ТЭС | D7: Месяц | E7: Плановый полезный отпуск тепловой энергии, в соответствии со сводным прогнозным балансом, Гкал | F7: Установленная тепловая мощность ТЭС, в соответствии со сводным прогнозным балансом, Гкал/час | G7: Количество часов в расчетном месяце, ч | H7: Использование установленной тепловой мощности ТЭС, % | I7: Минимально допустимая активная мощность на ТЭС, при которой функционирование энергосистемы не будет нарушено, МВт | J7: Установленная электрическая мощность ТЭС на плановый год, МВт | K7: Отношение величины минимально допустимой активной мощности ТЭС к установленной мощности ТЭС, % | L7: Уровень критичности ТЭС, % | M7: Для расчета "Категория уровня критичности" | N7: Категория уровня критичности
B8: 1 | C8: =#REF! -> #REF! | D8: январь | E8: 115510 | F8: 1169 | G8: =31*24 -> 744 | H8: =IF(F8*G8=0,0,E8/(F8*G8)*100) -> 13.281042 | I8: 0 | J8: =SUMIF(НЭЗТ!$F$6:$F$19,'Критичность ТЭС'!D8,НЭЗТ!$J$6:$J$19) -> 281.7 | K8: =IF(J8=0,0,I8/J8*100) -> 0 | L8: =(0.5*((SUMIFS(Справочники!$G$4:$L$4,Справочники!$G$6:$L$6,"<"&'Критичность ТЭС'!H8,Справочники!$G$7:$L$7,">="&'Критичность ТЭС'!H8))/5)+0.5*((SUMIFS(Справочники!$G$4:$L$4,Справочники!$G$8:$L$8,"<"&'Критичность ТЭС'!K8,Справочники!$G$9:$L$9,">="&'Критичность ТЭС'!K8))/5))*100 -> 30 | M8: =SUMIFS(#REF!,#REF!,"<="&'Критичность ТЭС'!L8,#REF!,">"&'Критичность ТЭС'!L8) -> #REF! | N8: =INDEX(#REF!,'Критичность ТЭС'!M8) -> #REF!
D9: февраль | E9: 98640 | F9: 1169 | G9: =28*24 -> 672 | H9: =IF(F9*G9=0,0,E9/(F9*G9)*100) -> 12.55652 | J9: =SUMIF(НЭЗТ!$F$6:$F$19,'Критичность ТЭС'!D9,НЭЗТ!$J$6:$J$19) -> 281.7 | K9: =IF(J9=0,0,I9/J9*100) -> 0 | L9: =(0.5*((SUMIFS(Справочники!$G$4:$L$4,Справочники!$G$6:$L$6,"<"&'Критичность ТЭС'!H9,Справочники!$G$7:$L$7,">="&'Критичность ТЭС'!H9))/5)+0.5*((SUMIFS(Справочники!$G$4:$L$4,Справочники!$G$8:$L$8,"<"&'Критичность ТЭС'!K9,Справочники!$G$9:$L$9,">="&'Критичность ТЭС'!K9))/5))*100 -> 30 | M9: =SUMIFS(#REF!,#REF!,"<="&'Критичность ТЭС'!L9,#REF!,">"&'Критичность ТЭС'!L9) -> #REF! | N9: =INDEX(#REF!,'Критичность ТЭС'!M9) -> #REF!
D10: март | E10: 73580 | F10: 1169 | G10: =31*24 -> 744 | H10: =IF(F10*G10=0,0,E10/(F10*G10)*100) -> 8.4600384 | J10: =SUMIF(НЭЗТ!$F$6:$F$19,'Критичность ТЭС'!D10,НЭЗТ!$J$6:$J$19) -> 281.7 | K10: =IF(J10=0,0,I10/J10*100) -> 0 | L10: =(0.5*((SUMIFS(Справочники!$G$4:$L$4,Справочники!$G$6:$L$6,"<"&'Критичность ТЭС'!H10,Справочники!$G$7:$L$7,">="&'Критичность ТЭС'!H10))/5)+0.5*((SUMIFS(Справочники!$G$4:$L$4,Справочники!$G$8:$L$8,"<"&'Критичность ТЭС'!K10,Справочники!$G$9:$L$9,">="&'Критичность ТЭС'!K10))/5))*100 -> 20 | M10: =SUMIFS(#REF!,#REF!,"<="&'Критичность ТЭС'!L10,#REF!,">"&'Критичность ТЭС'!L10) -> #REF! | N10: =INDEX(#REF!,'Критичность ТЭС'!M10) -> #REF!
D11: апрель | E11: 45900 | F11: 1169 | G11: =30*24 -> 720 | H11: =IF(F11*G11=0,0,E11/(F11*G11)*100) -> 5.453379 | J11: =SUMIF(НЭЗТ!$F$6:$F$19,'Критичность ТЭС'!D11,НЭЗТ!$J$6:$J$19) -> 280.3 | K11: =IF(J11=0,0,I11/J11*100) -> 0 | L11: =(0.5*((SUMIFS(Справочники!$G$4:$L$4,Справочники!$G$6:$L$6,"<"&'Критичность ТЭС'!H11,Справочники!$G$7:$L$7,">="&'Критичность ТЭС'!H11))/5)+0.5*((SUMIFS(Справочники!$G$4:$L$4,Справочники!$G$8:$L$8,"<"&'Критичность ТЭС'!K11,Справочники!$G$9:$L$9,">="&'Критичность ТЭС'!K11))/5))*100 -> 20 | M11: =SUMIFS(#REF!,#REF!,"<="&'Критичность ТЭС'!L11,#REF!,">"&'Критичность ТЭС'!L11) -> #REF! | N11: =INDEX(#REF!,'Критичность ТЭС'!M11) -> #REF!
D12: май | E12: 18330 | F12: 1169 | G12: =31*24 -> 744 | H12: =IF(F12*G12=0,0,E12/(F12*G12)*100) -> 2.1075361 | J12: =SUMIF(НЭЗТ!$F$6:$F$19,'Критичность ТЭС'!D12,НЭЗТ!$J$6:$J$19) -> 260 | K12: =IF(J12=0,0,I12/J12*100) -> 0 | L12: =(0.5*((SUMIFS(Справочники!$G$4:$L$4,Справочники!$G$6:$L$6,"<"&'Критичность ТЭС'!H12,Справочники!$G$7:$L$7,">="&'Критичность ТЭС'!H12))/5)+0.5*((SUMIFS(Справочники!$G$4:$L$4,Справочники!$G$8:$L$8,"<"&'Критичность ТЭС'!K12,Справочники!$G$9:$L$9,">="&'Критичность ТЭС'!K12))/5))*100 -> 10 | M12: =SUMIFS(#REF!,#REF!,"<="&'Критичность ТЭС'!L12,#REF!,">"&'Критичность ТЭС'!L12) -> #REF! | N12: =INDEX(#REF!,'Критичность ТЭС'!M12) -> #REF!
D13: июнь | E13: 14230 | F13: 1169 | G13: =30*24 -> 720 | H13: =IF(F13*G13=0,0,E13/(F13*G13)*100) -> 1.6906663 | J13: =SUMIF(НЭЗТ!$F$6:$F$19,'Критичность ТЭС'!D13,НЭЗТ!$J$6:$J$19) -> 260 | K13: =IF(J13=0,0,I13/J13*100) -> 0 | L13: =(0.5*((SUMIFS(Справочники!$G$4:$L$4,Справочники!$G$6:$L$6,"<"&'Критичность ТЭС'!H13,Справочники!$G$7:$L$7,">="&'Критичность ТЭС'!H13))/5)+0.5*((SUMIFS(Справочники!$G$4:$L$4,Справочники!$G$8:$L$8,"<"&'Критичность ТЭС'!K13,Справочники!$G$9:$L$9,">="&'Критичность ТЭС'!K13))/5))*100 -> 10 | M13: =SUMIFS(#REF!,#REF!,"<="&'Критичность ТЭС'!L13,#REF!,">"&'Критичность ТЭС'!L13) -> #REF! | N13: =INDEX(#REF!,'Критичность ТЭС'!M13) -> #REF!
D14: июль | E14: 12420 | F14: 1169 | G14: =31*24 -> 744 | H14: =IF(F14*G14=0,0,E14/(F14*G14)*100) -> 1.4280195 | J14: =SUMIF(НЭЗТ!$F$6:$F$19,'Критичность ТЭС'!D14,НЭЗТ!$J$6:$J$19) -> 260 | K14: =IF(J14=0,0,I14/J14*100) -> 0 | L14: =(0.5*((SUMIFS(Справочники!$G$4:$L$4,Справочники!$G$6:$L$6,"<"&'Критичность ТЭС'!H14,Справочники!$G$7:$L$7,">="&'Критичность ТЭС'!H14))/5)+0.5*((SUMIFS(Справочники!$G$4:$L$4,Справочники!$G$8:$L$8,"<"&'Критичность ТЭС'!K14,Справочники!$G$9:$L$9,">="&'Критичность ТЭС'!K14))/5))*100 -> 10 | M14: =SUMIFS(#REF!,#REF!,"<="&'Критичность ТЭС'!L14,#REF!,">"&'Критичность ТЭС'!L14) -> #REF! | N14: =INDEX(#REF!,'Критичность ТЭС'!M14) -> #REF!
D15: август | E15: 12160 | F15: 1169 | G15: =31*24 -> 744 | H15: =IF(F15*G15=0,0,E15/(F15*G15)*100) -> 1.3981254 | J15: =SUMIF(НЭЗТ!$F$6:$F$19,'Критичность ТЭС'!D15,НЭЗТ!$J$6:$J$19) -> 260 | K15: =IF(J15=0,0,I15/J15*100) -> 0 | L15: =(0.5*((SUMIFS(Справочники!$G$4:$L$4,Справочники!$G$6:$L$6,"<"&'Критичность ТЭС'!H15,Справочники!$G$7:$L$7,">="&'Критичность ТЭС'!H15))/5)+0.5*((SUMIFS(Справочники!$G$4:$L$4,Справочники!$G$8:$L$8,"<"&'Критичность ТЭС'!K15,Справочники!$G$9:$L$9,">="&'Критичность ТЭС'!K15))/5))*100 -> 10 | M15: =SUMIFS(#REF!,#REF!,"<="&'Критичность ТЭС'!L15,#REF!,">"&'Критичность ТЭС'!L15) -> #REF! | N15: =INDEX(#REF!,'Критичность ТЭС'!M15) -> #REF!
D16: сентябрь | E16: 14820 | F16: 1169 | G16: =30*24 -> 720 | H16: =IF(F16*G16=0,0,E16/(F16*G16)*100) -> 1.7607642 | J16: =SUMIF(НЭЗТ!$F$6:$F$19,'Критичность ТЭС'!D16,НЭЗТ!$J$6:$J$19) -> 260 | K16: =IF(J16=0,0,I16/J16*100) -> 0 | L16: =(0.5*((SUMIFS(Справочники!$G$4:$L$4,Справочники!$G$6:$L$6,"<"&'Критичность ТЭС'!H16,Справочники!$G$7:$L$7,">="&'Критичность ТЭС'!H16))/5)+0.5*((SUMIFS(Справочники!$G$4:$L$4,Справочники!$G$8:$L$8,"<"&'Критичность ТЭС'!K16,Справочники!$G$9:$L$9,">="&'Критичность ТЭС'!K16))/5))*100 -> 10 | M16: =SUMIFS(#REF!,#REF!,"<="&'Критичность ТЭС'!L16,#REF!,">"&'Критичность ТЭС'!L16) -> #REF! | N16: =INDEX(#REF!,'Критичность ТЭС'!M16) -> #REF!
D17: октябрь | E17: 46140 | F17: 1169 | G17: =31*24 -> 744 | H17: =IF(F17*G17=0,0,E17/(F17*G17)*100) -> 5.3050581 | J17: =SUMIF(НЭЗТ!$F$6:$F$19,'Критичность ТЭС'!D17,НЭЗТ!$J$6:$J$19) -> 275.7 | K17: =IF(J17=0,0,I17/J17*100) -> 0 | L17: =(0.5*((SUMIFS(Справочники!$G$4:$L$4,Справочники!$G$6:$L$6,"<"&'Критичность ТЭС'!H17,Справочники!$G$7:$L$7,">="&'Критичность ТЭС'!H17))/5)+0.5*((SUMIFS(Справочники!$G$4:$L$4,Справочники!$G$8:$L$8,"<"&'Критичность ТЭС'!K17,Справочники!$G$9:$L$9,">="&'Критичность ТЭС'!K17))/5))*100 -> 20 | M17: =SUMIFS(#REF!,#REF!,"<="&'Критичность ТЭС'!L17,#REF!,">"&'Критичность ТЭС'!L17) -> #REF! | N17: =INDEX(#REF!,'Критичность ТЭС'!M17) -> #REF!
D18: ноябрь | E18: 83060 | F18: 1169 | G18: =30*24 -> 720 | H18: =IF(F18*G18=0,0,E18/(F18*G18)*100) -> 9.8683585 | J18: =SUMIF(НЭЗТ!$F$6:$F$19,'Критичность ТЭС'!D18,НЭЗТ!$J$6:$J$19) -> 281.7 | K18: =IF(J18=0,0,I18/J18*100) -> 0 | L18: =(0.5*((SUMIFS(Справочники!$G$4:$L$4,Справочники!$G$6:$L$6,"<"&'Критичность ТЭС'!H18,Справочники!$G$7:$L$7,">="&'Критичность ТЭС'!H18))/5)+0.5*((SUMIFS(Справочники!$G$4:$L$4,Справочники!$G$8:$L$8,"<"&'Критичность ТЭС'!K18,Справочники!$G$9:$L$9,">="&'Критичность ТЭС'!K18))/5))*100 -> 20 | M18: =SUMIFS(#REF!,#REF!,"<="&'Критичность ТЭС'!L18,#REF!,">"&'Критичность ТЭС'!L18) -> #REF! | N18: =INDEX(#REF!,'Критичность ТЭС'!M18) -> #REF!
D19: декабрь | E19: 114730 | F19: 1169 | G19: =31*24 -> 744 | H19: =IF(F19*G19=0,0,E19/(F19*G19)*100) -> 13.191359 | J19: =SUMIF(НЭЗТ!$F$6:$F$19,'Критичность ТЭС'!D19,НЭЗТ!$J$6:$J$19) -> 281.7 | K19: =IF(J19=0,0,I19/J19*100) -> 0 | L19: =(0.5*((SUMIFS(Справочники!$G$4:$L$4,Справочники!$G$6:$L$6,"<"&'Критичность ТЭС'!H19,Справочники!$G$7:$L$7,">="&'Критичность ТЭС'!H19))/5)+0.5*((SUMIFS(Справочники!$G$4:$L$4,Справочники!$G$8:$L$8,"<"&'Критичность ТЭС'!K19,Справочники!$G$9:$L$9,">="&'Критичность ТЭС'!K19))/5))*100 -> 30 | M19: =SUMIFS(#REF!,#REF!,"<="&'Критичность ТЭС'!L19,#REF!,">"&'Критичность ТЭС'!L19) -> #REF! | N19: =INDEX(#REF!,'Критичность ТЭС'!M19) -> #REF!

Sheet Справочники
B2: Лист Критичность ТЭС
B3: Группа показателей | C3: Вес группы | D3: Показатель критичности | F3: Вес показателя | G3: Балл
G4: 0 | H4: 1 | I4: 2 | J4: 3 | K4: 4 | L4: 5
B6: Влияние на теплоснабжение | C6: 0.5 | D6: Использование уст тепл мощности, % | F6: 1 | G6: 0 | H6: 1e-15 | I6: 5 | J6: 10 | K6: 25 | L6: 40
G7: 0 | H7: 5 | I7: 10 | J7: 25 | K7: 40 | L7: 2000000000
B8: Влияние нагрузки ТЭС на электроэнергетический режим энергосистемы | C8: 0.5 | D8: Отношение величины минимально допустимой активной мощности ТЭС к установленной мощности ТЭС, % | F8: 1 | G8: 0 | H8: 10 | I8: 20 | J8: 30 | K8: 35 | L8: 40
G9: 10 | H9: 20 | I9: 30 | J9: 35 | K9: 40 | L9: 2000000000
B12: Трубопроводный способ доставки
B14: Аналитические показатели | C14: 0.5 | D14: Уровень резервирования топливоснабжения | F14: 0.7 | G14: Наличие резерва элементов ПС и ТХ | J14: Наличие резерва элементов ПС или ТХ | L14: Отсутствие резерва элементов ПС и ТХ
D15: Протяженность подводящего трубопровода, км | F15: 0.3 | H15: 1e-10 | I15: 1 | J15: 3 | K15: 5 | L15: 10
G16: 0 | H16: 1 | I16: 3 | J16: 5 | K16: 10 | L16: 2000000000 | M16: 0-расположение ТЭС на территории источника топлива
B18: Транспортный способ доставки
B20: Аналитические показатели | C20: 0.5 | D20: Количество точек отправки топлива | F20: 0.3 | G20: 3 | I20: 2 | L20: 1
D21: Средневзвеш. Время поставки топлива от разных поставщиков, суток | F21: 0.7 | G21: 0 | H21: 1 | I21: 1.5 | J21: 2 | K21: 2.5 | L21: 3
G22: 1 | H22: 1.5 | I22: 2 | J22: 2.5 | K22: 3 | L22: 2000000000
B24: Конвейерный способ доставки
B26: только Статистические
B28: Для всех способов доставки одинаковые
B30: Статистические | C30: 0.5 | D30: Статистика нарушений нормативов запасов топливаза последние 5 лет | F30: 0.5 | G30: 0 | H30: 1 | I30: 2 | J30: 4 | K30: 7 | L30: 10
G31: 0 | H31: 2 | I31: 4 | J31: 7 | K31: 10 | L31: 2000000000
D32: Отношение факт. Суточного использования топлива за последние 5 лет к количеству топлива для расчета базового НЭЗТ | F32: 0.5 | G32: 0 | H32: 0.1 | I32: 0.2 | J32: 0.4 | K32: 0.6 | L32: 0.8
G33: 0.1 | H33: 0.2 | I33: 0.4 | J33: 0.6 | K33: 0.8 | L33: 2000000000
